[
    {
        "code": "CMP96646",
        "firstName": "Adriana",
        "lastName": "Zapata",
        "phoneNumber": "097231782",
        "gender": "female",
        "birthYear": 1990,
        "idDepartment": 6,
        "municipiality": "Mun #1",
        "village": "Village #1",
        "idAssociation": 11,
        "farmName": "Farm #1",
        "location": "Location #1",
        "nrOfHa": 2.3,
        "nrCocoaHa": 0.5,
        "nrForestHa": 1.2,
        "nrCocoaLots": 2.5,
        "nrWaterSources": 4.3,
        "wildlife": "Mono_aullador Muchilero"
    },
    {
        "code": "CMP14013",
        "firstName": "Jose",
        "lastName": "H Agudelo",
        "phoneNumber": "097231782",
        "gender": "male",
        "birthYear": 1987,
        "idDepartment": 6,
        "municipiality": "Mun #1",
        "village": "Village #1",
        "idAssociation": 9,
        "farmName": "Farm #1",
        "location": "Location #1",
        "nrOfHa": 2.3,
        "nrCocoaHa": 0.5,
        "nrForestHa": 1.2,
        "nrCocoaLots": 2.5,
        "nrWaterSources": 4.3,
        "wildlife": "Mono_aullador Muchilero"
    },
    {
        "code": "CMP17690",
        "firstName": "Juventino",
        "lastName": "Perez",
        "phoneNumber": "097231782",
        "gender": "male",
        "birthYear": 1990,
        "idDepartment": 7,
        "municipiality": "Mun #1",
        "village": "Village #1",
        "idAssociation": 10,
        "farmName": "Farm #1",
        "location": "Location #1",
        "nrOfHa": 2.3,
        "nrCocoaHa": 0.5,
        "nrForestHa": 1.2,
        "nrCocoaLots": 2.5,
        "nrWaterSources": 4.3,
        "wildlife": "Mono_aullador Muchilero"
    },
    {
        "code": "CMP71345",
        "firstName": "Flor Dely",
        "lastName": "Coca",
        "phoneNumber": "097231782",
        "gender": "female",
        "birthYear": 1990,
        "idDepartment": 7,
        "municipiality": "Mun #1",
        "village": "Village #1",
        "idAssociation": 9,
        "farmName": "Farm #1",
        "location": "Location #1",
        "nrOfHa": 2.3,
        "nrCocoaHa": 0.5,
        "nrForestHa": 1.2,
        "nrCocoaLots": 2.5,
        "nrWaterSources": 4.3,
        "wildlife": "Mono_aullador Muchilero"
    },
    {
        "code": "CMP86056",
        "firstName": "Angelmiro",
        "lastName": "",
        "phoneNumber": "097231782",
        "gender": "male",
        "birthYear": 1993,
        "idDepartment": 6,
        "municipiality": "Mun #1",
        "village": "Village #1",
        "idAssociation": 11,
        "farmName": "Farm #1",
        "location": "Location #1",
        "nrOfHa": 2.3,
        "nrCocoaHa": 0.5,
        "nrForestHa": 1.2,
        "nrCocoaLots": 2.5,
        "nrWaterSources": 4.3,
        "wildlife": "Mono_aullador Muchilero"
    },
    {
        "code": "CMP05392",
        "firstName": "Flor Alba",
        "lastName": "Mendoza",
        "phoneNumber": "097231782",
        "gender": "female",
        "birthYear": 1998,
        "idDepartment": 7,
        "municipiality": "Mun #1",
        "village": "Village #1",
        "idAssociation": 9,
        "farmName": "Farm #1",
        "location": "Location #1",
        "nrOfHa": 2.3,
        "nrCocoaHa": 0.5,
        "nrForestHa": 1.2,
        "nrCocoaLots": 2.5,
        "nrWaterSources": 4.3,
        "wildlife": "Mono_aullador Muchilero"
    },
    {
        "code": "CMP28155",
        "firstName": "Lucila",
        "lastName": "Rondon",
        "phoneNumber": "097231782",
        "gender": "female",
        "birthYear": 1990,
        "idDepartment": 6,
        "municipiality": "Mun #1",
        "village": "Village #1",
        "idAssociation": 10,
        "farmName": "Farm #1",
        "location": "Location #1",
        "nrOfHa": 2.3,
        "nrCocoaHa": 0.5,
        "nrForestHa": 1.2,
        "nrCocoaLots": 2.5,
        "nrWaterSources": 4.3,
        "wildlife": "Mono_aullador Muchilero"
    },
    {
        "code": "CMP14219",
        "firstName": "Humberto",
        "lastName": "Rangel",
        "phoneNumber": "097231782",
        "gender": "male",
        "birthYear": 1990,
        "idDepartment": 6,
        "municipiality": "Mun #1",
        "village": "Village #1",
        "idAssociation": 10,
        "farmName": "Farm #1",
        "location": "Location #1",
        "nrOfHa": 2.3,
        "nrCocoaHa": 0.5,
        "nrForestHa": 1.2,
        "nrCocoaLots": 2.5,
        "nrWaterSources": 4.3,
        "wildlife": "Mono_aullador Muchilero"
    },
    {
        "code": "CMP22964",
        "firstName": "Deyanid",
        "lastName": "Prada",
        "phoneNumber": "097231782",
        "gender": "male",
        "birthYear": 1990,
        "idDepartment": 7,
        "municipiality": "Mun #1",
        "village": "Village #1",
        "idAssociation": 9,
        "farmName": "Farm #1",
        "location": "Location #1",
        "nrOfHa": 2.3,
        "nrCocoaHa": 0.5,
        "nrForestHa": 1.2,
        "nrCocoaLots": 2.5,
        "nrWaterSources": 4.3,
        "wildlife": "Mono_aullador Muchilero"
    }
]